drlab_minilib/__init__.py
drlab_minilib/minilib.py
drlab_minilib-0.3.1.dist-info/METADATA
drlab_minilib-0.3.1.dist-info/WHEEL
drlab_minilib-0.3.1.dist-info/top_level.txt
drlab_minilib-0.3.1.dist-info/RECORD
